sanicdb.py
sanicdb-0.2.dist-info/METADATA
sanicdb-0.2.dist-info/RECORD
sanicdb-0.2.dist-info/WHEEL
sanicdb-0.2.dist-info/top_level.txt
