Metadata-Version: 2.1
Name: sanicdb
Version: 0.2
Summary: A lightweight wrapper around aiomysql.Pool for easy to use
Requires-Dist: pymysql
Requires-Dist: aiomysql
